forgedata/__init__.py
forgedata/countries.csv
forgedata/domains-common.csv
forgedata/domains.csv
forgedata/firstname-female.csv
forgedata/firstname-male.csv
forgedata/generator.py
forgedata/lastname.csv
forgedata-1.0.1.dist-info/LICENSE
forgedata-1.0.1.dist-info/METADATA
forgedata-1.0.1.dist-info/WHEEL
forgedata-1.0.1.dist-info/top_level.txt
forgedata-1.0.1.dist-info/RECORD
