Metadata-Version: 2.1
Name: forgedata
Version: 1.0.1
Summary: A Python package for generating random dummy data for testing purposes.
Home-page: https://github.com/ITSSOUMIT/ForgeData
Author: Soumit Das
Author-email: its.soumit.das@gmail.com
Classifier: Programming Language :: Python :: 3
Classifier: License :: OSI Approved :: MIT License
Classifier: Operating System :: OS Independent
Requires-Python: >=3.7
License-File: LICENSE
Requires-Dist: pandas
